vremoteapi/__init__.py
vremoteapi/main.py
vremoteapi/OLD_/__init__.py
vremoteapi/OLD_/command.py
vremoteapi/OLD_/dispatcher.py
vremoteapi/OLD_/factories.py
vremoteapi/OLD_/require_signature.py
vremoteapi/OLD_/type_checking.py
vremoteapi/OLD_/types_.py
vremoteapi/remote_api.py
vremoteapi-0.1.12.dist-info/WHEEL
vremoteapi-0.1.12.dist-info/METADATA
vremoteapi-0.1.12.dist-info/RECORD
